LICENSE
MANIFEST.in
README.rst
setup.py
create_admin/__init__.py
create_admin/management/__init__.py
create_admin/management/commands/__init__.py
create_admin/management/commands/createadmin.py
create_admin/tests/__init__.py
create_admin/tests/conftest.py
create_admin/tests/test_create_admin.py
django_create_admin.egg-info/PKG-INFO
django_create_admin.egg-info/SOURCES.txt
django_create_admin.egg-info/dependency_links.txt
django_create_admin.egg-info/requires.txt
django_create_admin.egg-info/top_level.txt